indicam_client/__init__.py
indicam_client/indicam_client.py
indicam_client-1.0.9.dist-info/LICENSE
indicam_client-1.0.9.dist-info/WHEEL
indicam_client-1.0.9.dist-info/METADATA
indicam_client-1.0.9.dist-info/RECORD
