Metadata-Version: 2.1
Name: indicam_client
Version: 1.0.9
Summary: A thin client for the IndiCam Service.
Author-email: HausNet Admin <admin@hausnet.io>
Requires-Python: <4
Classifier: License :: OSI Approved :: MIT License
Requires-Dist: aiohttp
Project-URL: Documentation, https://docs.hausnet.io/indicam
Project-URL: Home, https://hausnet.io
